python_package/__init__.py
python_package/mod_pack.py
python_package/Area_package/__init__.py
python_package/Area_package/rectangle.py
python_package/Area_package/triangle.py
python_package/volume_package/__init__.py
python_package/volume_package/cube.py
python_package/volume_package/cuboid.py
PICABO-0.1.dist-info/LICENSE.txt
PICABO-0.1.dist-info/METADATA
PICABO-0.1.dist-info/WHEEL
PICABO-0.1.dist-info/top_level.txt
PICABO-0.1.dist-info/RECORD
